README.md
setup.py
mcaio/__init__.py
mcaio/cli.py
mcaio/client.py
mcaio.egg-info/PKG-INFO
mcaio.egg-info/SOURCES.txt
mcaio.egg-info/dependency_links.txt
mcaio.egg-info/entry_points.txt
mcaio.egg-info/top_level.txt