Metadata-Version: 2.1
Name: mcaio
Version: 0.2.1
Summary: Asynс lib to get information about Minecraft server
Home-page: https://git.orudo.ru/trueold89/mcaio
Author: trueold89
Author-email: trueold89@orudo.ru
